pypkg_manager/__init__.py
pypkg_manager/commands.py
pypkg_manager/pypkg_manager.py
pypkg_manager-0.0.1.dist-info/LICENSE
pypkg_manager-0.0.1.dist-info/METADATA
pypkg_manager-0.0.1.dist-info/WHEEL
pypkg_manager-0.0.1.dist-info/entry_points.txt
pypkg_manager-0.0.1.dist-info/top_level.txt
pypkg_manager-0.0.1.dist-info/RECORD
